{"nodes": [{"id": "home_lyo_self_project_migration_ares_tests_test_probe_spec_c", "label": "test_probe_spec.c", "file_type": "code", "source_file": "tests/test_probe_spec.c", "source_location": "L1"}, {"id": "tests_test_probe_spec_noop_log", "label": "noop_log()", "file_type": "code", "source_file": "tests/test_probe_spec.c", "source_location": "L14"}, {"id": "tests_test_probe_spec_parse", "label": "parse()", "file_type": "code", "source_file": "tests/test_probe_spec.c", "source_location": "L17"}, {"id": "tests_test_probe_spec_main", "label": "main()", "file_type": "code", "source_file": "tests/test_probe_spec.c", "source_location": "L24"}], "edges": [{"source": "home_lyo_self_project_migration_ares_tests_test_probe_spec_c", "target": "probe_resolve", "relation": "imports", "context": "import", "confidence": "EXTRACTED", "source_file": "tests/test_probe_spec.c", "source_location": "L5", "weight": 1.0}, {"source": "home_lyo_self_project_migration_ares_tests_test_probe_spec_c", "target": "stdio", "relation": "imports", "context": "import", "confidence": "EXTRACTED", "source_file": "tests/test_probe_spec.c", "source_location": "L7", "weight": 1.0}, {"source": "home_lyo_self_project_migration_ares_tests_test_probe_spec_c", "target": "string", "relation": "imports", "context": "import", "confidence": "EXTRACTED", "source_file": "tests/test_probe_spec.c", "source_location": "L8", "weight": 1.0}, {"source": "home_lyo_self_project_migration_ares_tests_test_probe_spec_c", "target": "tests_test_probe_spec_noop_log", "relation": "contains", "confidence": "EXTRACTED", "source_file": "tests/test_probe_spec.c", "source_location": "L14", "weight": 1.0}, {"source": "home_lyo_self_project_migration_ares_tests_test_probe_spec_c", "target": "tests_test_probe_spec_parse", "relation": "contains", "confidence": "EXTRACTED", "source_file": "tests/test_probe_spec.c", "source_location": "L17", "weight": 1.0}, {"source": "home_lyo_self_project_migration_ares_tests_test_probe_spec_c", "target": "tests_test_probe_spec_main", "relation": "contains", "confidence": "EXTRACTED", "source_file": "tests/test_probe_spec.c", "source_location": "L24", "weight": 1.0}, {"source": "tests_test_probe_spec_main", "target": "tests_test_probe_spec_parse", "relation": "calls", "context": "call", "confidence": "EXTRACTED", "source_file": "tests/test_probe_spec.c", "source_location": "L27", "weight": 1.0}], "raw_calls": [{"caller_nid": "tests_test_probe_spec_parse", "callee": "parse_custom_probe_spec", "is_member_call": false, "source_file": "/home/lyo/self-project/migration/ARES/tests/test_probe_spec.c", "source_location": "L17", "receiver": null}, {"caller_nid": "tests_test_probe_spec_main", "callee": "CHECK", "is_member_call": false, "source_file": "/home/lyo/self-project/migration/ARES/tests/test_probe_spec.c", "source_location": "L27", "receiver": null}, {"caller_nid": "tests_test_probe_spec_main", "callee": "CHECK", "is_member_call": false, "source_file": "/home/lyo/self-project/migration/ARES/tests/test_probe_spec.c", "source_location": "L28", "receiver": null}, {"caller_nid": "tests_test_probe_spec_main", "callee": "strcmp", "is_member_call": false, "source_file": "/home/lyo/self-project/migration/ARES/tests/test_probe_spec.c", "source_location": "L28", "receiver": null}, {"caller_nid": "tests_test_probe_spec_main", "callee": "CHECK", "is_member_call": false, "source_file": "/home/lyo/self-project/migration/ARES/tests/test_probe_spec.c", "source_location": "L29", "receiver": null}, {"caller_nid": "tests_test_probe_spec_main", "callee": "strcmp", "is_member_call": false, "source_file": "/home/lyo/self-project/migration/ARES/tests/test_probe_spec.c", "source_location": "L29", "receiver": null}, {"caller_nid": "tests_test_probe_spec_main", "callee": "CHECK", "is_member_call": false, "source_file": "/home/lyo/self-project/migration/ARES/tests/test_probe_spec.c", "source_location": "L30", "receiver": null}, {"caller_nid": "tests_test_probe_spec_main", "callee": "CHECK", "is_member_call": false, "source_file": "/home/lyo/self-project/migration/ARES/tests/test_probe_spec.c", "source_location": "L31", "receiver": null}, {"caller_nid": "tests_test_probe_spec_main", "callee": "CHECK", "is_member_call": false, "source_file": "/home/lyo/self-project/migration/ARES/tests/test_probe_spec.c", "source_location": "L32", "receiver": null}, {"caller_nid": "tests_test_probe_spec_main", "callee": "CHECK", "is_member_call": false, "source_file": "/home/lyo/self-project/migration/ARES/tests/test_probe_spec.c", "source_location": "L33", "receiver": null}, {"caller_nid": "tests_test_probe_spec_main", "callee": "CHECK", "is_member_call": false, "source_file": "/home/lyo/self-project/migration/ARES/tests/test_probe_spec.c", "source_location": "L36", "receiver": null}, {"caller_nid": "tests_test_probe_spec_main", "callee": "CHECK", "is_member_call": false, "source_file": "/home/lyo/self-project/migration/ARES/tests/test_probe_spec.c", "source_location": "L37", "receiver": null}, {"caller_nid": "tests_test_probe_spec_main", "callee": "CHECK", "is_member_call": false, "source_file": "/home/lyo/self-project/migration/ARES/tests/test_probe_spec.c", "source_location": "L38", "receiver": null}, {"caller_nid": "tests_test_probe_spec_main", "callee": "CHECK", "is_member_call": false, "source_file": "/home/lyo/self-project/migration/ARES/tests/test_probe_spec.c", "source_location": "L41", "receiver": null}, {"caller_nid": "tests_test_probe_spec_main", "callee": "CHECK", "is_member_call": false, "source_file": "/home/lyo/self-project/migration/ARES/tests/test_probe_spec.c", "source_location": "L42", "receiver": null}, {"caller_nid": "tests_test_probe_spec_main", "callee": "CHECK", "is_member_call": false, "source_file": "/home/lyo/self-project/migration/ARES/tests/test_probe_spec.c", "source_location": "L45", "receiver": null}, {"caller_nid": "tests_test_probe_spec_main", "callee": "CHECK", "is_member_call": false, "source_file": "/home/lyo/self-project/migration/ARES/tests/test_probe_spec.c", "source_location": "L46", "receiver": null}, {"caller_nid": "tests_test_probe_spec_main", "callee": "CHECK", "is_member_call": false, "source_file": "/home/lyo/self-project/migration/ARES/tests/test_probe_spec.c", "source_location": "L47", "receiver": null}, {"caller_nid": "tests_test_probe_spec_main", "callee": "CHECK", "is_member_call": false, "source_file": "/home/lyo/self-project/migration/ARES/tests/test_probe_spec.c", "source_location": "L50", "receiver": null}, {"caller_nid": "tests_test_probe_spec_main", "callee": "CHECK", "is_member_call": false, "source_file": "/home/lyo/self-project/migration/ARES/tests/test_probe_spec.c", "source_location": "L51", "receiver": null}, {"caller_nid": "tests_test_probe_spec_main", "callee": "strcmp", "is_member_call": false, "source_file": "/home/lyo/self-project/migration/ARES/tests/test_probe_spec.c", "source_location": "L51", "receiver": null}, {"caller_nid": "tests_test_probe_spec_main", "callee": "CHECK", "is_member_call": false, "source_file": "/home/lyo/self-project/migration/ARES/tests/test_probe_spec.c", "source_location": "L52", "receiver": null}, {"caller_nid": "tests_test_probe_spec_main", "callee": "CHECK", "is_member_call": false, "source_file": "/home/lyo/self-project/migration/ARES/tests/test_probe_spec.c", "source_location": "L55", "receiver": null}, {"caller_nid": "tests_test_probe_spec_main", "callee": "CHECK", "is_member_call": false, "source_file": "/home/lyo/self-project/migration/ARES/tests/test_probe_spec.c", "source_location": "L56", "receiver": null}, {"caller_nid": "tests_test_probe_spec_main", "callee": "strcmp", "is_member_call": false, "source_file": "/home/lyo/self-project/migration/ARES/tests/test_probe_spec.c", "source_location": "L56", "receiver": null}, {"caller_nid": "tests_test_probe_spec_main", "callee": "CHECK", "is_member_call": false, "source_file": "/home/lyo/self-project/migration/ARES/tests/test_probe_spec.c", "source_location": "L59", "receiver": null}, {"caller_nid": "tests_test_probe_spec_main", "callee": "CHECK", "is_member_call": false, "source_file": "/home/lyo/self-project/migration/ARES/tests/test_probe_spec.c", "source_location": "L60", "receiver": null}, {"caller_nid": "tests_test_probe_spec_main", "callee": "CHECK", "is_member_call": false, "source_file": "/home/lyo/self-project/migration/ARES/tests/test_probe_spec.c", "source_location": "L64", "receiver": null}, {"caller_nid": "tests_test_probe_spec_main", "callee": "CHECK", "is_member_call": false, "source_file": "/home/lyo/self-project/migration/ARES/tests/test_probe_spec.c", "source_location": "L65", "receiver": null}, {"caller_nid": "tests_test_probe_spec_main", "callee": "CHECK", "is_member_call": false, "source_file": "/home/lyo/self-project/migration/ARES/tests/test_probe_spec.c", "source_location": "L69", "receiver": null}, {"caller_nid": "tests_test_probe_spec_main", "callee": "CHECK", "is_member_call": false, "source_file": "/home/lyo/self-project/migration/ARES/tests/test_probe_spec.c", "source_location": "L70", "receiver": null}, {"caller_nid": "tests_test_probe_spec_main", "callee": "CHECK", "is_member_call": false, "source_file": "/home/lyo/self-project/migration/ARES/tests/test_probe_spec.c", "source_location": "L74", "receiver": null}, {"caller_nid": "tests_test_probe_spec_main", "callee": "CHECK", "is_member_call": false, "source_file": "/home/lyo/self-project/migration/ARES/tests/test_probe_spec.c", "source_location": "L75", "receiver": null}, {"caller_nid": "tests_test_probe_spec_main", "callee": "CHECK", "is_member_call": false, "source_file": "/home/lyo/self-project/migration/ARES/tests/test_probe_spec.c", "source_location": "L78", "receiver": null}, {"caller_nid": "tests_test_probe_spec_main", "callee": "CHECK", "is_member_call": false, "source_file": "/home/lyo/self-project/migration/ARES/tests/test_probe_spec.c", "source_location": "L79", "receiver": null}, {"caller_nid": "tests_test_probe_spec_main", "callee": "CHECK", "is_member_call": false, "source_file": "/home/lyo/self-project/migration/ARES/tests/test_probe_spec.c", "source_location": "L80", "receiver": null}, {"caller_nid": "tests_test_probe_spec_main", "callee": "CHECK", "is_member_call": false, "source_file": "/home/lyo/self-project/migration/ARES/tests/test_probe_spec.c", "source_location": "L81", "receiver": null}, {"caller_nid": "tests_test_probe_spec_main", "callee": "CHECK", "is_member_call": false, "source_file": "/home/lyo/self-project/migration/ARES/tests/test_probe_spec.c", "source_location": "L82", "receiver": null}, {"caller_nid": "tests_test_probe_spec_main", "callee": "CHECK", "is_member_call": false, "source_file": "/home/lyo/self-project/migration/ARES/tests/test_probe_spec.c", "source_location": "L83", "receiver": null}, {"caller_nid": "tests_test_probe_spec_main", "callee": "printf", "is_member_call": false, "source_file": "/home/lyo/self-project/migration/ARES/tests/test_probe_spec.c", "source_location": "L85", "receiver": null}]}